c3d_parser/__init__.py
c3d_parser/application.py
c3d_parser/core/c3d_parser.py
c3d_parser/core/c3d_patch.py
c3d_parser/core/osim.py
c3d_parser/core/utils.py
c3d_parser/core/osim_resources/external_loads_template.xml
c3d_parser/core/osim_resources/ik_task_set.xml
c3d_parser/settings/general.py
c3d_parser/settings/logging.py
c3d_parser/settings/marker_maps/AUC.json
c3d_parser/settings/marker_maps/FMC.json
c3d_parser/settings/marker_maps/MH.json
c3d_parser/settings/marker_maps/QCMAS.json
c3d_parser/settings/marker_maps/RBWH.json
c3d_parser/settings/marker_maps/RCH.json
c3d_parser/settings/marker_maps/Sydney.json
c3d_parser/view/main_window.py
c3d_parser/view/utils.py
c3d_parser/view/widgets.py
c3d_parser/view/dialogs/about_dialog.py
c3d_parser/view/dialogs/marker_set_dialog.py
c3d_parser/view/dialogs/marker_set_import_dialog.py
c3d_parser/view/dialogs/options_dialog.py
c3d_parser/view/ui/ui_main_window.py
c3d_parser/view/ui/ui_marker_set_dialog.py
c3d_parser/view/ui/ui_marker_set_import_dialog.py
c3d_parser/view/ui/ui_options_dialog.py
c3d_parser-0.2.3.dist-info/licenses/LICENSE
c3d_parser-0.2.3.dist-info/METADATA
c3d_parser-0.2.3.dist-info/WHEEL
c3d_parser-0.2.3.dist-info/entry_points.txt
c3d_parser-0.2.3.dist-info/top_level.txt
c3d_parser-0.2.3.dist-info/RECORD
