Metadata-Version: 2.4
Name: c3d-parser
Version: 0.2.3
Summary: C3D parser for gait data harmonisation.
Author-email: Timothy Salemink <tim.nicolas@outlook.com>, Sally Jack <sallyjaack@gmail.com>
License-Expression: Apache-2.0
Project-URL: Repository, https://github.com/tsalemink/C3D-parser
License-File: LICENSE
Requires-Dist: scipy
Requires-Dist: numpy==1.26.4
Requires-Dist: pandas
Requires-Dist: c3d==0.5.2
Requires-Dist: trc-data-reader
Requires-Dist: opensim-model-creator>=0.1.15
Requires-Dist: PySide6
Requires-Dist: matplotlib
Requires-Dist: mplcursors
Dynamic: license-file
